chunky/__about__.py
chunky/__init__.py
chunky/core.py
chunky/loaders.py
chunky/pipeline.py
chunky/registry.py
chunky/types.py
chunky/chunkers/__init__.py
chunky/chunkers/_common.py
chunky/chunkers/fallback.py
chunky/chunkers/fortran.py
chunky/chunkers/markdown.py
chunky/chunkers/python.py
chunky/chunkers/text.py
chunky/chunkers/treesitter.py
chunky/chunkers/yaml_json.py
chunky_files-1.0.0.dist-info/METADATA
chunky_files-1.0.0.dist-info/WHEEL
chunky_files-1.0.0.dist-info/licenses/LICENSE
chunky_files-1.0.0.dist-info/RECORD
