Metadata-Version: 2.4
Name: chunky-files
Version: 1.0.0
Summary: Semantic chunking utilities for scientific code and documentation corpora.
Project-URL: Home, https://github.com/AmberLee2427/chunky
Project-URL: Documentation, https://chunky.readthedocs.io/
Project-URL: Issues, https://github.com/AmberLee2427/chunky/issues
Author: Nancy Brain Contributors
License: MIT License
License-File: LICENSE
Classifier: Development Status :: 3 - Alpha
Classifier: Intended Audience :: Developers
Classifier: Intended Audience :: Science/Research
Classifier: License :: OSI Approved :: MIT License
Classifier: Programming Language :: Python
Classifier: Programming Language :: Python :: 3
Classifier: Programming Language :: Python :: 3.8
Classifier: Programming Language :: Python :: 3.9
Classifier: Programming Language :: Python :: 3.10
Classifier: Programming Language :: Python :: 3.11
Classifier: Programming Language :: Python :: 3.12
Classifier: Topic :: Scientific/Engineering
Classifier: Topic :: Text Processing :: Linguistic
Requires-Python: >=3.8
Provides-Extra: dev
Requires-Dist: bump-my-version>=0.6; extra == 'dev'
Requires-Dist: coverage[toml]>=7; extra == 'dev'
Requires-Dist: pytest-cov>=4; extra == 'dev'
Requires-Dist: pytest>=7; extra == 'dev'
Requires-Dist: ruff>=0.6; extra == 'dev'
Requires-Dist: tree-sitter-languages>=1.10.2; extra == 'dev'
Requires-Dist: tree-sitter==0.20.1; extra == 'dev'
Provides-Extra: docs
Requires-Dist: furo>=2024.0.0; extra == 'docs'
Requires-Dist: myst-parser>=2; extra == 'docs'
Requires-Dist: sphinx>=7; extra == 'docs'
Provides-Extra: tree
Requires-Dist: tree-sitter-languages>=1.10.2; extra == 'tree'
Requires-Dist: tree-sitter==0.20.1; extra == 'tree'
